{
  "section": {
    "id": "social-profiles",
    "title": "Social Profiles",
    "visibility": "public",
    "displayOrder": 99
  },

  "profiles": [
    {
      "id": "github",
      "platform": "GitHub",
      "username": "alsopranab",
      "url": "https://github.com/alsopranab",
      "icon": "github",
      "category": "developer",
      "priority": 1,
      "enabled": true,
      "verified": true
    },
    {
      "id": "linkedin",
      "platform": "LinkedIn",
      "username": "alsopranab",
      "url": "https://linkedin.com/in/alsopranab",
      "icon": "linkedin",
      "category": "professional",
      "priority": 2,
      "enabled": true,
      "verified": true
    },
    {
      "id": "leetcode",
      "platform": "LeetCode",
      "username": "alsopranab",
      "url": "https://leetcode.com/alsopranab",
      "icon": "leetcode",
      "category": "competitive-programming",
      "priority": 3,
      "enabled": true,
      "verified": true
    },
    {
      "id": "hackerrank",
      "platform": "HackerRank",
      "username": "alsopranab",
      "url": "https://www.hackerrank.com/alsopranab",
      "icon": "hackerrank",
      "category": "competitive-programming",
      "priority": 4,
      "enabled": true,
      "verified": true
    },
    {
      "id": "instagram",
      "platform": "Instagram",
      "username": "the.queryguy",
      "url": "https://instagram.com/the.queryguy",
      "icon": "instagram",
      "category": "social",
      "priority": 5,
      "enabled": true,
      "verified": false
    }
  ],

  "meta": {
    "version": "1.0.0",
    "schema": "social.profiles.v1",
    "maintainedBy": "self",
    "lastUpdated": "2025-01-01"
  }
}
